beautiful_print/__init__.py
beautiful_print/beautiful.py
elegant_io/__init__.py
elegant_io/elegant_print.py
elegant_io-0.0.1.dist-info/METADATA
elegant_io-0.0.1.dist-info/WHEEL
elegant_io-0.0.1.dist-info/top_level.txt
elegant_io-0.0.1.dist-info/RECORD
