Metadata-Version: 2.1
Name: elegant-io
Version: 0.0.1
Summary: An elegant io package
Home-page: https://github.com/jiayingwang/elegant_io
Author: Jiaying Wang
Author-email: jiaying@sjzu.edu.cn
License: UNKNOWN
Platform: UNKNOWN
Classifier: Programming Language :: Python :: 3
Classifier: License :: OSI Approved :: MIT License
Classifier: Operating System :: OS Independent
Requires-Python: >=3.6
